<?xml version="1.0"?>
<company><item><名称>清泰小区 南北通透 格局好 两房 两厅 房东诚心出售</名称><URL>https://hz.lianjia.com/ershoufang/103101602681.html</URL><小区名称>清泰小区 </小区名称><规格> | 2室2厅 | 68.09平米 | 南 北 | 精装 | 无电梯</规格><楼层>高楼层(共7层)1996年建板楼  -  采荷</楼层><价格>296</价格><单价>单价43472元/平米</单价><关注度>8人关注 / 共2次带看 / 8天以前发布</关注度></item><item><名称>大三房，20方大露台，私家花园</名称><URL>https://hz.lianjia.com/ershoufang/103101602925.html</URL><小区名称>岸上蓝山 </小区名称><规格> | 3室2厅 | 108.75平米 | 南 北 | 其他 | 无电梯</规格><楼层>中楼层(共5层)2013年建板楼  -  闲林</楼层><价格>235</价格><单价>单价21610元/平米</单价><关注度>9人关注 / 共2次带看 / 8天以前发布</关注度></item><item><名称>满五唯一，带入户花园， 附带面积大，保养好拎包入住 </名称><URL>https://hz.lianjia.com/ershoufang/103101603123.html</URL><小区名称>坤和西溪里璞园 </小区名称><规格> | 2室2厅 | 89.24平米 | 南 北 | 精装 | 有电梯</规格><楼层>低楼层(共12层)2010年建板楼  -  西溪</楼层><价格>410</价格><单价>单价45944元/平米</单价><关注度>1人关注 / 共1次带看 / 8天以前发布</关注度></item><item><名称>文苑小区大两房 位置好 诚心出售 带四平方储藏室</名称><URL>https://hz.lianjia.com/ershoufang/103101599874.html</URL><小区名称>文苑小区 </小区名称><规格> | 2室2厅 | 81.84平米 | 南 | 简装 | 无电梯</规格><楼层>低楼层(共6层)1996年建板楼  -  嘉绿</楼层><价格>300</价格><单价>单价36657元/平米</单价><关注度>0人关注 / 共1次带看 / 9天以前发布</关注度></item><item><名称>锦秀兰庭 总价低 全明户型  诚心出售</名称><URL>https://hz.lianjia.com/ershoufang/103101601396.html</URL><小区名称>锦秀兰庭 </小区名称><规格> | 2室2厅 | 80.1平米 | 南 | 其他 | 有电梯</规格><楼层>中楼层(共18层)2000年建板楼  -  桥西</楼层><价格>288</价格><单价>单价35956元/平米</单价><关注度>3人关注 / 共2次带看 / 8天以前发布</关注度></item><item><名称>南北透通，满五唯一免双税，带车位，带200方大露台。</名称><URL>https://hz.lianjia.com/ershoufang/103101601402.html</URL><小区名称>怡景花城鸣翠苑 </小区名称><规格> | 3室2厅 | 123.9平米 | 南 北 | 其他 | 无电梯</规格><楼层>中楼层(共5层)2006年建板楼  -  闲林</楼层><价格>280</价格><单价>单价22599元/平米</单价><关注度>4人关注 / 共1次带看 / 8天以前发布</关注度></item><item><名称>阳光郡电梯三房精装修楼层好！！！</名称><URL>https://hz.lianjia.com/ershoufang/103101597647.html</URL><小区名称>阳光郡 </小区名称><规格> | 2室1厅 | 85.21平米 | 南 | 精装 | 有电梯</规格><楼层>低楼层(共28层)2014年建塔楼  -  三墩</楼层><价格>290</价格><单价>单价34034元/平米</单价><关注度>8人关注 / 共2次带看 / 9天以前发布</关注度></item><item><名称> 此房楼采光好，南北通风好， 视野好，小区交通便利。</名称><URL>https://hz.lianjia.com/ershoufang/103101598347.html</URL><小区名称>通惠丽港 </小区名称><规格> | 3室2厅 | 129.9平米 | 南 | 其他 | 有电梯</规格><楼层>高楼层(共18层)板楼  -  萧山新城区</楼层><价格>280</价格><单价>单价21556元/平米</单价><关注度>9人关注 / 共4次带看 / 9天以前发布</关注度></item><item><名称>精装修 满2年 loft户型 房东急售</名称><URL>https://hz.lianjia.com/ershoufang/103101599402.html</URL><小区名称>凯丽晶座 </小区名称><规格> | 2室2厅 | 62.75平米 | 南 | 其他</规格><楼层>中楼层(共22层)2013年建塔楼  -  萧山开发区</楼层><价格>120</价格><单价>单价19124元/平米</单价><关注度>12人关注 / 共1次带看 / 9天以前发布</关注度></item><item><名称>钱江水晶城，满两年，采光充足，配套齐全。</名称><URL>https://hz.lianjia.com/ershoufang/103101579837.html</URL><小区名称>钱江水晶城 </小区名称><规格> | 3室2厅 | 89.17平米 | 南 | 其他 | 有电梯</规格><楼层>中楼层(共34层)2011年建板楼  -  彩虹城</楼层><价格>505</价格><单价>单价56634元/平米</单价><关注度>9人关注 / 共2次带看 / 14天以前发布</关注度></item><item><名称>金地自在城   开发商精装修  保养好   户型方正</名称><URL>https://hz.lianjia.com/ershoufang/103101580915.html</URL><小区名称>金地自在城 </小区名称><规格> | 3室1厅 | 89平米 | 南 北 | 精装 | 有电梯</规格><楼层>低楼层(共26层)2012年建板楼  -  三墩</楼层><价格>330</价格><单价>单价37079元/平米</单价><关注度>6人关注 / 共1次带看 / 14天以前发布</关注度></item><item><名称>宝龙云滨湾边套，南北通透，户型很正，中间楼层</名称><URL>https://hz.lianjia.com/ershoufang/103101580925.html</URL><小区名称>宝龙云滨湾 </小区名称><规格> | 2室2厅 | 89平米 | 南 | 其他 | 有电梯</规格><楼层>中楼层(共18层)2012年建塔楼  -  高教园区东</楼层><价格>235</价格><单价>单价26405元/平米</单价><关注度>5人关注 / 共3次带看 / 14天以前发布</关注度></item><item><名称>精装修地铁 三房 家电家具 带车位 诚心出售</名称><URL>https://hz.lianjia.com/ershoufang/103101580974.html</URL><小区名称>滨江金色江南 </小区名称><规格> | 3室2厅 | 89平米 | 南 北 | 其他 | 有电梯</规格><楼层>低楼层(共27层)2016年建板塔结合  -  钱江世纪城</楼层><价格>405</价格><单价>单价45506元/平米</单价><关注度>12人关注 / 共5次带看 / 14天以前发布</关注度></item><item><名称>仓基新村 两房南一房北 全明户型 楼层好 卖小本部</名称><URL>https://hz.lianjia.com/ershoufang/103101581682.html</URL><小区名称>仓基新村 </小区名称><规格> | 3室1厅 | 71.99平米 | 南 北 | 其他 | 无电梯</规格><楼层>中楼层(共6层)1988年建板楼  -  信义坊</楼层><价格>260</价格><单价>单价36117元/平米</单价><关注度>14人关注 / 共3次带看 / 14天以前发布</关注度></item><item><名称>世纪坊 胜利天地  精装修 房东急售</名称><URL>https://hz.lianjia.com/ershoufang/103101582105.html</URL><小区名称>世纪坊 </小区名称><规格> | 3室2厅 | 100.51平米 | 南 北 | 其他 | 无电梯</规格><楼层>低楼层(共7层)1998年建板楼  -  近江</楼层><价格>450</价格><单价>单价44772元/平米</单价><关注度>5人关注 / 共3次带看 / 14天以前发布</关注度></item><item><名称>精装修，彩虹城平层三房，可拎包入住。</名称><URL>https://hz.lianjia.com/ershoufang/103101583194.html</URL><小区名称>彩虹城 </小区名称><规格> | 3室2厅 | 147.37平米 | 南 | 精装 | 有电梯</规格><楼层>低楼层(共20层)2007年建板楼  -  彩虹城</楼层><价格>560</价格><单价>单价38000元/平米</单价><关注度>8人关注 / 共2次带看 / 13天以前发布</关注度></item><item><名称>皮市巷 顶楼跃层 精装两房 带露台 阳光好</名称><URL>https://hz.lianjia.com/ershoufang/103101584530.html</URL><小区名称>皮市巷 </小区名称><规格> | 2室2厅 | 97平米 | 南 | 其他 | 无电梯</规格><楼层>高楼层(共6层)2000年建板楼  -  清泰</楼层><价格>380</价格><单价>单价39176元/平米</单价><关注度>7人关注 / 共1次带看 / 13天以前发布</关注度></item><item><名称>此房免增值税 30万硬装三开间朝南 楼层好视野开阔</名称><URL>https://hz.lianjia.com/ershoufang/103101584739.html</URL><小区名称>金马名仕园 </小区名称><规格> | 3室2厅 | 157平米 | 南 | 精装 | 有电梯</规格><楼层>高楼层(共21层)  -  萧山市区</楼层><价格>340</价格><单价>单价21657元/平米</单价><关注度>5人关注 / 共2次带看 / 13天以前发布</关注度></item><item><名称>铭雅苑东区  采光好 交通便利 户型好</名称><URL>https://hz.lianjia.com/ershoufang/103101584947.html</URL><小区名称>铭雅苑东区 </小区名称><规格> | 2室2厅 | 82.74平米 | 南 北 | 其他 | 无电梯</规格><楼层>高楼层(共6层)2004年建板楼  -  三墩</楼层><价格>248</价格><单价>单价29974元/平米</单价><关注度>10人关注 / 共1次带看 / 13天以前发布</关注度></item><item><名称>两房朝南精装修，全明西边套，低总价，房东诚心出售</名称><URL>https://hz.lianjia.com/ershoufang/103101587198.html</URL><小区名称>嘉绿景苑西园 </小区名称><规格> | 2室1厅 | 72.61平米 | 南 | 其他 | 有电梯</规格><楼层>中楼层(共16层)2006年建板楼  -  文三西路</楼层><价格>280</价格><单价>单价38563元/平米</单价><关注度>14人关注 / 共5次带看 / 13天以前发布</关注度></item><item><名称>三房朝南 西边套 可见江景 采光好</名称><URL>https://hz.lianjia.com/ershoufang/103101587239.html</URL><小区名称>近江家园三园 </小区名称><规格> | 3室2厅 | 135.84平米 | 南 | 简装 | 有电梯</规格><楼层>低楼层(共18层)2002年建塔楼  -  近江</楼层><价格>620</价格><单价>单价45642元/平米</单价><关注度>2人关注 / 共1次带看 / 13天以前发布</关注度></item><item><名称>四开间朝南  中间楼层  阳光无限好</名称><URL>https://hz.lianjia.com/ershoufang/103101587742.html</URL><小区名称>潮鸣苑 </小区名称><规格> | 4室2厅 | 119.96平米 | 南 北 | 其他 | 无电梯</规格><楼层>中楼层(共7层)1994年建板楼  -  潮鸣</楼层><价格>420</价格><单价>单价35012元/平米</单价><关注度>7人关注 / 共4次带看 / 12天以前发布</关注度></item><item><名称>满五唯一 精装超便宜的大三房！！！</名称><URL>https://hz.lianjia.com/ershoufang/103101588157.html</URL><小区名称>南岸晶都花园 </小区名称><规格> | 3室2厅 | 133平米 | 南 | 其他 | 有电梯</规格><楼层>低楼层(共26层)2007年建板楼  -  长河</楼层><价格>400</价格><单价>单价30076元/平米</单价><关注度>8人关注 / 共1次带看 / 12天以前发布</关注度></item><item><名称>精装修带空调全明户型无遮挡通透</名称><URL>https://hz.lianjia.com/ershoufang/103101591447.html</URL><小区名称>新城西溪逸境 </小区名称><规格> | 3室2厅 | 88.48平米 | 南 北 | 其他 | 有电梯</规格><楼层>中楼层(共11层)2016年建板楼  -  未来科技城</楼层><价格>280</价格><单价>单价31646元/平米</单价><关注度>21人关注 / 共1次带看 / 11天以前发布</关注度></item><item><名称>东新园望景苑优质中间套，客厅带窗，透气性好。</名称><URL>https://hz.lianjia.com/ershoufang/103101592051.html</URL><小区名称>东新园望景苑 </小区名称><规格> | 2室2厅 | 102.87平米 | 南 | 其他 | 有电梯</规格><楼层>低楼层(共11层)2004年建板楼  -  三塘</楼层><价格>280</价格><单价>单价27219元/平米</单价><关注度>4人关注 / 共1次带看 / 11天以前发布</关注度></item><item><名称>保利罗兰香谷 大户型 看房方便</名称><URL>https://hz.lianjia.com/ershoufang/103101592261.html</URL><小区名称>保利罗兰香谷 </小区名称><规格> | 3室2厅 | 89.39平米 | 南 北 | 其他 | 有电梯</规格><楼层>低楼层(共17层)2015年建板楼  -  丁桥</楼层><价格>205</价格><单价>单价22934元/平米</单价><关注度>2人关注 / 共2次带看 / 11天以前发布</关注度></item><item><名称>三里家园 刚需神房 两房朝南 南北通 有储藏间</名称><URL>https://hz.lianjia.com/ershoufang/103101592490.html</URL><小区名称>三里家园一区 </小区名称><规格> | 2室1厅 | 67.72平米 | 南 | 简装 | 无电梯</规格><楼层>低楼层(共6层)2006年建板楼  -  三里亭</楼层><价格>238</价格><单价>单价35145元/平米</单价><关注度>5人关注 / 共2次带看 / 11天以前发布</关注度></item><item><名称>欣盛东方郡东区。免双税、自住精装修、空间利用足</名称><URL>https://hz.lianjia.com/ershoufang/103101594159.html</URL><小区名称>欣盛东方郡东区 </小区名称><规格> | 2室2厅 | 88平米 | 南 | 其他 | 有电梯</规格><楼层>中楼层(共33层)2009年建板楼  -  滨江区政府</楼层><价格>420</价格><单价>单价47728元/平米</单价><关注度>11人关注 / 共1次带看 / 10天以前发布</关注度></item><item><名称>刚需两房毛坯 全南户型 业主诚售 目前出租 满五且唯一</名称><URL>https://hz.lianjia.com/ershoufang/103101595714.html</URL><小区名称>北城铭苑 </小区名称><规格> | 2室2厅 | 61.67平米 | 南 北 | 毛坯</规格><楼层>低楼层(共17层)2000年建板楼  -  丁桥</楼层><价格>135</价格><单价>单价21891元/平米</单价><关注度>14人关注 / 共1次带看 / 10天以前发布</关注度></item><item><名称>滨江物业 高品质小区 环境优美 纯毛坯</名称><URL>https://hz.lianjia.com/ershoufang/103101597384.html</URL><小区名称>滨江曙光之城 </小区名称><规格> | 3室2厅 | 89平米 | 南 北 | 简装 | 有电梯</规格><楼层>低楼层(共15层)2011年建塔楼  -  火车东站</楼层><价格>385</价格><单价>单价43259元/平米</单价><关注度>0人关注 / 共1次带看 / 9天以前发布</关注度></item></company>
